ngql_gen/__init__.py
ngql_gen/config/__init__.py
ngql_gen/config/config.py
ngql_gen/generator/__init__.py
ngql_gen/generator/edge.py
ngql_gen/generator/edge_type.py
ngql_gen/generator/select.py
ngql_gen/generator/space.py
ngql_gen/generator/tag.py
ngql_gen/generator/utils.py
ngql_gen/generator/vertex.py
ngql_gen/model/__init__.py
ngql_gen/model/edge_type.py
ngql_gen/model/tag.py
ngql_gen-0.0.8.dist-info/LICENSE
ngql_gen-0.0.8.dist-info/METADATA
ngql_gen-0.0.8.dist-info/WHEEL
ngql_gen-0.0.8.dist-info/top_level.txt
ngql_gen-0.0.8.dist-info/RECORD
