Metadata-Version: 2.1
Name: ngql-gen
Version: 0.0.8
Summary: Nebula Graph Query Language Generator
Author-email: 东南dnf <zjy2414@outlook.com>
License: Apache License
Project-URL: Home, https://github.com/zjy2414
Classifier: License :: OSI Approved :: Apache Software License
License-File: LICENSE
Requires-Dist: pyyaml
Requires-Dist: nebula3-python
